intelix/__init__.py
intelix-0.1.2.dist-info/METADATA
intelix-0.1.2.dist-info/WHEEL
intelix-0.1.2.dist-info/top_level.txt
intelix-0.1.2.dist-info/RECORD
