Metadata-Version: 2.1
Name: intelix
Version: 0.1.2
Summary: Sophos Labs Intelix Client
Home-page: UNKNOWN
Author: Stephen OLeary
Author-email: stephen.oleary@sophos.com
License: UNKNOWN
Platform: UNKNOWN
